biocframe/__init__.py
biocframe/frame.py
biocframe/io/__init__.py
biocframe/io/from_pandas.py
biocframe-0.7.1.dist-info/licenses/LICENSE.txt
biocframe-0.7.1.dist-info/METADATA
biocframe-0.7.1.dist-info/WHEEL
biocframe-0.7.1.dist-info/top_level.txt
biocframe-0.7.1.dist-info/RECORD
