Metadata-Version: 2.4
Name: BiocFrame
Version: 0.7.1
Summary: Flexible dataframe representation to support nested structures.
Home-page: https://github.com/BiocPy/biocframe
Author: Jayaram Kancherla
Author-email: jayaram.kancherla@gmail.com
License: MIT
Project-URL: Documentation, https://github.com/BiocPy/biocframe
Project-URL: Source, https://github.com/BiocPy/biocframe
Platform: any
Classifier: Development Status :: 4 - Beta
Classifier: Programming Language :: Python
Requires-Python: >=3.9
License-File: LICENSE.txt
Requires-Dist: importlib-metadata; python_version < "3.8"
Requires-Dist: biocutils>=0.3.1
Requires-Dist: numpy
Provides-Extra: optional
Requires-Dist: pandas; extra == "optional"
Requires-Dist: polars; extra == "optional"
Provides-Extra: testing
Requires-Dist: setuptools; extra == "testing"
Requires-Dist: pytest; extra == "testing"
Requires-Dist: pytest-cov; extra == "testing"
Requires-Dist: pandas; extra == "testing"
Requires-Dist: polars; extra == "testing"
Dynamic: license-file
